dirmap/__init__.py
dirmap/manifest.json
dirmap/orbit_directory_mapper.py
dirmap/settings.json
dirmap/helpers/__init__.py
dirmap/helpers/manifest_helper.py
dirmap/helpers/update_checker.py
dirmap/utils/__init__.py
dirmap/utils/arborescence_util.py
dirmap/utils/orbit_tree_builder.py
dirmap/utils/settings_manager.py
dirmap/utils/settings_menu.py
directory_mapper-1.7.3.dist-info/LICENSE.md
directory_mapper-1.7.3.dist-info/LICENSE.txt
directory_mapper-1.7.3.dist-info/METADATA
directory_mapper-1.7.3.dist-info/WHEEL
directory_mapper-1.7.3.dist-info/entry_points.txt
directory_mapper-1.7.3.dist-info/top_level.txt
directory_mapper-1.7.3.dist-info/RECORD
