Metadata-Version: 2.1
Name: directory-mapper
Version: 1.7.3
Summary: Directory Mapper - A tool for mapping directories and visualizing file structures.
Home-page: https://github.com/orbitturner/directory-mapper
Author: Mohamed Gueye (Orbit Turner)
Author-email: orbitturner@gmail.com
License: CC BY-NC-SA 4.0 DEED
Project-URL: Bug Tracker, https://github.com/orbitturner/directory-mapper/issues/new
Classifier: Programming Language :: Python :: 3.8
Classifier: Operating System :: OS Independent
Requires-Python: >=3.7
License-File: LICENSE.md
License-File: LICENSE.txt
Requires-Dist: art ==6.1
Requires-Dist: certifi ==2024.2.2
Requires-Dist: charset-normalizer ==3.3.2
Requires-Dist: colorama ==0.4.6
Requires-Dist: idna ==3.6
Requires-Dist: loguru ==0.7.2
Requires-Dist: markdown-it-py ==3.0.0
Requires-Dist: mdurl ==0.1.2
Requires-Dist: Pygments ==2.17.2
Requires-Dist: PyYAML ==6.0.1
Requires-Dist: requests ==2.31.0
Requires-Dist: rich ==13.7.0
Requires-Dist: termcolor ==2.4.0
Requires-Dist: urllib3 ==2.2.0
Requires-Dist: win32-setctime ==1.1.0
Requires-Dist: wonderwords ==2.2.0
Requires-Dist: setuptools ==69.2.0
